livereload/__init__.py
livereload/handlers.py
livereload/middleware.py
livereload/server.py
livereload/watcher.py
livereload/management/__init__.py
livereload/management/commands/__init__.py
livereload/management/commands/livereload.py
livereload/management/commands/runserver.py
livereload/templatetags/__init__.py
livereload/templatetags/livereload_tags.py
livereload/vendors/livereload.js
django_livereload_server-0.5.1.dist-info/LICENSE
django_livereload_server-0.5.1.dist-info/METADATA
django_livereload_server-0.5.1.dist-info/WHEEL
django_livereload_server-0.5.1.dist-info/top_level.txt
django_livereload_server-0.5.1.dist-info/RECORD
