Metadata-Version: 2.1
Name: django-livereload-server
Version: 0.5.1
Summary: LiveReload functionality integrated with your Django development environment
Home-page: https://github.com/tjwalch/django-livereload-server
Author: Tomas Walch
Author-email: tomaswalch@gmail.com
License: BSD License
Keywords: django,server,runserver,livereload
Classifier: Framework :: Django
Classifier: Environment :: Web Environment
Classifier: Programming Language :: Python
Classifier: Programming Language :: Python :: 3
Classifier: Intended Audience :: Developers
Classifier: Operating System :: OS Independent
Classifier: License :: OSI Approved :: BSD License
Classifier: Topic :: Software Development :: Libraries :: Python Modules
License-File: LICENSE
Requires-Dist: django>=1.8
Requires-Dist: tornado
